mestra_jobs
