Metadata-Version: 2.4
Name: mestra-jobs
Version: 0.1.4
Summary: Lib responsavel por gerenciar task e jobs para executar determinadas tarefas
Home-page: https://bitbucket.org/mestra1/jobs_lib
Author: Mestra
Author-email: mestraac@gmail.com
Keywords: mestra_job
Classifier: Programming Language :: Python :: 3
Classifier: Operating System :: OS Independent
License-File: LICENSE
Dynamic: author
Dynamic: author-email
Dynamic: classifier
Dynamic: description
Dynamic: description-content-type
Dynamic: home-page
Dynamic: keywords
Dynamic: license-file
Dynamic: summary
